interactive_trader/__init__.py
interactive_trader/ibkr_app.py
interactive_trader/synchronous_functions.py
interactive_trader-0.1.3.dist-info/LICENSE
interactive_trader-0.1.3.dist-info/METADATA
interactive_trader-0.1.3.dist-info/WHEEL
interactive_trader-0.1.3.dist-info/top_level.txt
interactive_trader-0.1.3.dist-info/RECORD
