Metadata-Version: 2.1
Name: interactive-trader
Version: 0.1.3
Summary: Trade on Interactive Brokers with Plotly Dash in Python
Home-page: https://interactive-trader.readthedocs.io/
Author: Jake Vestal
Author-email: jmv13@duke.edu
License: MIT
Platform: UNKNOWN
Classifier: Intended Audience :: Developers
Classifier: License :: OSI Approved :: MIT License
Classifier: Programming Language :: Python
Classifier: Programming Language :: Python :: 3
Classifier: Programming Language :: Python :: 3.7
Classifier: Programming Language :: Python :: 3.8
Classifier: Programming Language :: Python :: 3.9
Classifier: Programming Language :: Python :: 3.10
Classifier: Operating System :: OS Independent
License-File: LICENSE
Requires-Dist: pandas
Requires-Dist: dash
Requires-Dist: ibapi
Requires-Dist: dash-bootstrap-components
